narwhals_daft/__init__.py
narwhals_daft/dataframe.py
narwhals_daft/expr.py
narwhals_daft/expr_dt.py
narwhals_daft/expr_list.py
narwhals_daft/expr_name.py
narwhals_daft/expr_str.py
narwhals_daft/group_by.py
narwhals_daft/namespace.py
narwhals_daft/selectors.py
narwhals_daft/utils.py
narwhals_daft-0.4.1.dist-info/METADATA
narwhals_daft-0.4.1.dist-info/WHEEL
narwhals_daft-0.4.1.dist-info/entry_points.txt
narwhals_daft-0.4.1.dist-info/licenses/LICENSE.md
narwhals_daft-0.4.1.dist-info/RECORD
