Metadata-Version: 2.4
Name: narwhals_daft
Version: 0.4.1
License-File: LICENSE.md
Requires-Python: >=3.10
Requires-Dist: daft>=0.5.18
Requires-Dist: narwhals>=2.10.0
